opensarlab_frontend/__init__.py
opensarlab_frontend/_version.py
opensarlab_frontend/handlers.py
opensarlab_frontend/handles/controlbtn.py
opensarlab_frontend/handles/disk_space.py
opensarlab_frontend/handles/oslnotify.py
opensarlab_frontend/handles/profile_label.py
opensarlab_frontend/handles/oslnotify_lib/calendar.py
opensarlab_frontend/handles/oslnotify_lib/storage.py
opensarlab_frontend-1.5.1.data/data/etc/jupyter/jupyter_server_config.d/opensarlab_frontend.json
opensarlab_frontend-1.5.1.data/data/share/jupyter/labextensions/opensarlab_frontend/package.json
opensarlab_frontend-1.5.1.data/data/share/jupyter/labextensions/opensarlab_frontend/schemas/opensarlab_frontend/package.json.orig
opensarlab_frontend-1.5.1.data/data/share/jupyter/labextensions/opensarlab_frontend/schemas/opensarlab_frontend/plugin.json
opensarlab_frontend-1.5.1.data/data/share/jupyter/labextensions/opensarlab_frontend/static/747.03ecac097cb834c2e1ec.js
opensarlab_frontend-1.5.1.data/data/share/jupyter/labextensions/opensarlab_frontend/static/754.d8e9315eca72e935004d.js
opensarlab_frontend-1.5.1.data/data/share/jupyter/labextensions/opensarlab_frontend/static/901.0f2141243fa32b537202.js
opensarlab_frontend-1.5.1.data/data/share/jupyter/labextensions/opensarlab_frontend/static/901.0f2141243fa32b537202.js.LICENSE.txt
opensarlab_frontend-1.5.1.data/data/share/jupyter/labextensions/opensarlab_frontend/static/remoteEntry.454d399f6d581277d089.js
opensarlab_frontend-1.5.1.data/data/share/jupyter/labextensions/opensarlab_frontend/static/style.js
opensarlab_frontend-1.5.1.data/data/share/jupyter/labextensions/opensarlab_frontend/static/third-party-licenses.json
opensarlab_frontend-1.5.1.data/data/share/jupyter/labextensions/opensarlab_frontend/install.json
opensarlab_frontend-1.5.1.dist-info/METADATA
opensarlab_frontend-1.5.1.dist-info/WHEEL
opensarlab_frontend-1.5.1.dist-info/licenses/LICENSE
opensarlab_frontend-1.5.1.dist-info/RECORD
