Metadata-Version: 2.1
Name: opensarlab_frontend
Version: 1.5.1
Summary: A JupyterLab extension.
Project-URL: Homepage, https://github.com/ASFOpenSARlab/opensarlab-extensions/blob/main/README.md
Project-URL: Bug Tracker, https://github.com/ASFOpenSARlab/opensarlab-extensions/blob/main/README.md/issues
Project-URL: Repository, https://github.com/ASFOpenSARlab/opensarlab-extensions/blob/main/README.md.git
Author-email: OpenSARLab Admin <uaf-jupyterhub-asf@alaska.edu>
License: BSD 3-Clause License
License-File: LICENSE
Classifier: Framework :: Jupyter
Classifier: Framework :: Jupyter :: JupyterLab
Classifier: Framework :: Jupyter :: JupyterLab :: 4
Classifier: Framework :: Jupyter :: JupyterLab :: Extensions
Classifier: Framework :: Jupyter :: JupyterLab :: Extensions :: Prebuilt
Classifier: License :: OSI Approved :: BSD License
Classifier: Programming Language :: Python
Classifier: Programming Language :: Python :: 3
Classifier: Programming Language :: Python :: 3.8
Classifier: Programming Language :: Python :: 3.9
Classifier: Programming Language :: Python :: 3.10
Classifier: Programming Language :: Python :: 3.11
Requires-Python: >=3.8
Requires-Dist: jupyter-server<3,>=2.0.1
